chitrakala/__init__.py
chitrakala-0.0.1.dist-info/LICENSE
chitrakala-0.0.1.dist-info/METADATA
chitrakala-0.0.1.dist-info/WHEEL
chitrakala-0.0.1.dist-info/top_level.txt
chitrakala-0.0.1.dist-info/RECORD
